query_builder.pyi
query_builder/__init__.py
query_builder/__init__.pyi
query_builder/py.typed
query_builder/query_builder.abi3.so
query_builder_tool-0.2.1.dist-info/METADATA
query_builder_tool-0.2.1.dist-info/WHEEL
query_builder_tool-0.2.1.dist-info/licenses/LICENSE
query_builder_tool-0.2.1.dist-info/RECORD
