Metadata-Version: 2.4
Name: query-builder-tool
Version: 0.2.1
Classifier: Development Status :: 4 - Beta
Classifier: Intended Audience :: Developers
Classifier: License :: OSI Approved :: MIT License
Classifier: Operating System :: MacOS
Classifier: Operating System :: MacOS :: MacOS X
Classifier: Programming Language :: Python :: 3
Classifier: Programming Language :: Python :: 3.8
Classifier: Programming Language :: Python :: 3.9
Classifier: Programming Language :: Python :: 3.10
Classifier: Programming Language :: Python :: 3.11
Classifier: Programming Language :: Python :: 3.12
Classifier: Programming Language :: Rust
Classifier: Topic :: Database
Classifier: Topic :: Security
Classifier: Topic :: Software Development :: Libraries :: Python Modules
License-File: LICENSE
Summary: A secure SQL query builder for Python using Rust and pyo3. Supports dynamic templates with safety checks against SQL injection.
Keywords: sql,query,builder,security,rust,pyo3
Author-email: 缪克拉 <2972799448@qq.com>
Requires-Python: >=3.8, <3.13
Project-URL: Homepage, https://github.com/miaokela/query-builder
Project-URL: Repository, https://github.com/miaokela/query-builder
Project-URL: Documentation, https://github.com/miaokela/query-builder#readme
Project-URL: Bug Tracker, https://github.com/miaokela/query-builder/issues
